scisort/__init__.py
scisort/_version.py
scisort/api.py
scisort/keygen.py
scisort-0.5.3.dist-info/LICENSE
scisort-0.5.3.dist-info/METADATA
scisort-0.5.3.dist-info/WHEEL
scisort-0.5.3.dist-info/top_level.txt
scisort-0.5.3.dist-info/RECORD
