Metadata-Version: 2.1
Name: scisort
Version: 0.5.3
Summary: Smart sorting algorithm for files and folders in research projects and repositories
Author-email: Jonathan de Bruin <jonathandebruinos@gmail.com>
License: MIT
Classifier: Development Status :: 5 - Production/Stable
Classifier: License :: OSI Approved :: MIT License
Classifier: Programming Language :: Python :: 3.6
Classifier: Programming Language :: Python :: 3.7
Classifier: Programming Language :: Python :: 3.8
Classifier: Programming Language :: Python :: 3.9
Classifier: Programming Language :: Python :: 3.10
Requires-Python: >=3.6
Provides-Extra: lint
Provides-Extra: test
License-File: LICENSE
